mir/linca.py
mir.linca-0.1.0.dist-info/DESCRIPTION.rst
mir.linca-0.1.0.dist-info/METADATA
mir.linca-0.1.0.dist-info/RECORD
mir.linca-0.1.0.dist-info/WHEEL
mir.linca-0.1.0.dist-info/entry_points.txt
mir.linca-0.1.0.dist-info/metadata.json
mir.linca-0.1.0.dist-info/top_level.txt
