Metadata-Version: 2.0
Name: mir.linca
Version: 0.1.0
Summary: Link new files in watched directory elsewhere.
Home-page: https://github.com/darkfeline/mir.linca
Author: Allen Li
Author-email: darkfeline@felesatra.moe
License: UNKNOWN
Platform: UNKNOWN
Classifier: Development Status :: 4 - Beta
Classifier: Environment :: Console
Classifier: Intended Audience :: End Users/Desktop
Classifier: Programming Language :: Python :: 3.5
